fortiosapi/__init__.py
fortiosapi/exceptions.py
fortiosapi/fortiosapi.py
tests/__init__.py
tests/test_fortiosapi_virsh.py
fortiosapi-1.0.5.dist-info/LICENSE
fortiosapi-1.0.5.dist-info/METADATA
fortiosapi-1.0.5.dist-info/WHEEL
fortiosapi-1.0.5.dist-info/top_level.txt
fortiosapi-1.0.5.dist-info/RECORD
