Metadata-Version: 2.1
Name: fortiosapi
Version: 1.0.5
Summary: Python modules to use Fortigate APIs
Home-page: https://github.com/fortinet-solutions-cse/fortiosapi
Author: Nicolas Thomas
Author-email: nthomas@fortinet.com
License: UNKNOWN
Keywords: Fortinet fortigate fortios rest api
Platform: UNKNOWN
Classifier: Development Status :: 5 - Production/Stable
Classifier: License :: OSI Approved :: Apache Software License
Classifier: Programming Language :: Python 
Classifier: Topic :: Security
